gurpreet/__init__.py
gurpreet/__main__.py
Topsis_Gurpreet_102003070-1.0.0.dist-info/METADATA
Topsis_Gurpreet_102003070-1.0.0.dist-info/WHEEL
Topsis_Gurpreet_102003070-1.0.0.dist-info/entry_points.txt
Topsis_Gurpreet_102003070-1.0.0.dist-info/top_level.txt
Topsis_Gurpreet_102003070-1.0.0.dist-info/RECORD
