Metadata-Version: 2.1
Name: Topsis-Gurpreet-102003070
Version: 1.0.0
Summary: Topsis package for MCDM problems
Author: Gurpreet Singh
Author-email: gurpreet.gsr50@gmail.com
Classifier: Programming Language :: Python :: 3
Classifier: Programming Language :: Python :: 3.6
Classifier: Programming Language :: Python :: 3.7
Classifier: License :: OSI Approved :: MIT License
Classifier: Operating System :: OS Independent
Requires-Python: >=3.6
Requires-Dist: pandas
